{
  "event_type": "external_governance_interoperability_audit",
  "timestamp_utc": "$(date -u +"%Y-%m-%dT%H:%M:%SZ")",
  "target_system": "AquariuOS",
  "audit_classification": "Execution-Time Governance Infrastructure Audit",
  "governance_focus": [
    "governance drift",
    "decision boundaries",
    "runtime enforcement",
    "telemetry continuity",
    "survivable accountability",
    "authority binding",
    "behavioral accumulation"
  ],
  "identified_risks": [
    "founder centralization risk",
    "interpretive governance drift",
    "accountability diffusion",
    "narrative capture risk",
    "runtime ambiguity",
    "telemetry insufficiency"
  ],
  "artifact_reference": "audits/aquarios_audit/HHI_AQUARIUOS_GOVERNANCE_MESSAGE_01.md",
  "artifact_sha256": "ffbb64ae94249a69d34e8d7aff27f38967e5f34ab70dc181442977fccdc73865",
  "git_commit": "72235e32076a74793ef63cc32be316e913c377cf",
  "telemetry_status": "persistent",
  "evidence_continuity": "active",
  "replayability": "enabled",
  "checksum_validation": "verified"
}
